setup.cfg
setup.py
nginx_redis_cache/__init__.py
nginx_redis_cache/clients.py
nginx_redis_cache/decorators.py
nginx_redis_cache/middleware.py
nginx_redis_cache.egg-info/PKG-INFO
nginx_redis_cache.egg-info/SOURCES.txt
nginx_redis_cache.egg-info/dependency_links.txt
nginx_redis_cache.egg-info/requires.txt
nginx_redis_cache.egg-info/top_level.txt