Metadata-Version: 1.1
Name: nginx-redis-cache
Version: 0.1
Summary: Library to aid the integration of a Redis cache for use in Django applications sitting behind Nginx. test lib
Home-page: https://bitbucket.org/justcompile/django-nginx-redis-cache
Author: Richard Hayes
Author-email: rich@justcompile.it
License: UNKNOWN
Download-URL: https://bitbucket.org/justcompile/django-nginx-redis-cache/get/0.1.tar.gz
Keywords: django,caching,nginx,redis
Platform: UNKNOWN
